google/cloud/billing/__init__.py
google/cloud/billing/gapic_version.py
google/cloud/billing/py.typed
google/cloud/billing_v1/__init__.py
google/cloud/billing_v1/gapic_metadata.json
google/cloud/billing_v1/gapic_version.py
google/cloud/billing_v1/py.typed
google/cloud/billing_v1/services/__init__.py
google/cloud/billing_v1/services/cloud_billing/__init__.py
google/cloud/billing_v1/services/cloud_billing/async_client.py
google/cloud/billing_v1/services/cloud_billing/client.py
google/cloud/billing_v1/services/cloud_billing/pagers.py
google/cloud/billing_v1/services/cloud_billing/transports/__init__.py
google/cloud/billing_v1/services/cloud_billing/transports/base.py
google/cloud/billing_v1/services/cloud_billing/transports/grpc.py
google/cloud/billing_v1/services/cloud_billing/transports/grpc_asyncio.py
google/cloud/billing_v1/services/cloud_billing/transports/rest.py
google/cloud/billing_v1/services/cloud_billing/transports/rest_base.py
google/cloud/billing_v1/services/cloud_catalog/__init__.py
google/cloud/billing_v1/services/cloud_catalog/async_client.py
google/cloud/billing_v1/services/cloud_catalog/client.py
google/cloud/billing_v1/services/cloud_catalog/pagers.py
google/cloud/billing_v1/services/cloud_catalog/transports/__init__.py
google/cloud/billing_v1/services/cloud_catalog/transports/base.py
google/cloud/billing_v1/services/cloud_catalog/transports/grpc.py
google/cloud/billing_v1/services/cloud_catalog/transports/grpc_asyncio.py
google/cloud/billing_v1/services/cloud_catalog/transports/rest.py
google/cloud/billing_v1/services/cloud_catalog/transports/rest_base.py
google/cloud/billing_v1/types/__init__.py
google/cloud/billing_v1/types/cloud_billing.py
google/cloud/billing_v1/types/cloud_catalog.py
google_cloud_billing-1.16.2.dist-info/LICENSE
google_cloud_billing-1.16.2.dist-info/METADATA
google_cloud_billing-1.16.2.dist-info/WHEEL
google_cloud_billing-1.16.2.dist-info/top_level.txt
google_cloud_billing-1.16.2.dist-info/RECORD
